odoo/addons/stock_reservation_date_show/README.rst
odoo/addons/stock_reservation_date_show/__init__.py
odoo/addons/stock_reservation_date_show/__manifest__.py
odoo/addons/stock_reservation_date_show/i18n/it.po
odoo/addons/stock_reservation_date_show/i18n/stock_reservation_date_show.pot
odoo/addons/stock_reservation_date_show/readme/CONTRIBUTORS.rst
odoo/addons/stock_reservation_date_show/readme/DESCRIPTION.rst
odoo/addons/stock_reservation_date_show/static/description/icon.png
odoo/addons/stock_reservation_date_show/static/description/index.html
odoo/addons/stock_reservation_date_show/views/stock_move_views.xml
odoo/addons/stock_reservation_date_show/views/stock_picking_views.xml
odoo_addon_stock_reservation_date_show-16.0.1.0.0.3.dist-info/METADATA
odoo_addon_stock_reservation_date_show-16.0.1.0.0.3.dist-info/WHEEL
odoo_addon_stock_reservation_date_show-16.0.1.0.0.3.dist-info/top_level.txt
odoo_addon_stock_reservation_date_show-16.0.1.0.0.3.dist-info/RECORD
